clok/__init__.py
clok/client.py
clok/cron.py
clok/log.py
clok/radio.py
clok/server.py
clok/models/__init__.py
clok/models/alarm.py
clok/models/base.py
clok/models/webradio.py
clok/static/bower_components/director/build/director.min.js
clok/static/bower_components/font-awesome/css/font-awesome.css
clok/static/bower_components/font-awesome/css/font-awesome.min.css
clok/static/bower_components/font-awesome/fonts/fontawesome-webfont.ttf
clok/static/bower_components/lodash/dist/lodash.core.min.js
clok/static/bower_components/lodash/dist/lodash.fp.min.js
clok/static/bower_components/lodash/dist/lodash.min.js
clok/static/bower_components/lodash/vendor/firebug-lite/skin/xp/debugger.css
clok/static/bower_components/lodash/vendor/firebug-lite/skin/xp/firebug-1.3a2.css
clok/static/bower_components/lodash/vendor/firebug-lite/skin/xp/firebug.IE6.css
clok/static/bower_components/lodash/vendor/firebug-lite/skin/xp/firebug.css
clok/static/bower_components/lodash/vendor/firebug-lite/skin/xp/html.css
clok/static/bower_components/pure-min/index.css
clok/static/bower_components/qwest/qwest.min.js
clok/static/bower_components/vue/dist/vue.min.js
clok/static/bower_components/vue-i18n/dist/vue-i18n.min.js
clok/static/css/main.css
clok/static/html/index.html
clok/static/js/app.js
clok/static/js/translation.js
clok/tests/__init__.py
clok/tests/conftest.py
clok/tests/test_cron.py
clok/tests/test_log.py
clok/tests/test_models.py
clok/tests/test_radio.py
clok-2.0.2.dist-info/DESCRIPTION.rst
clok-2.0.2.dist-info/METADATA
clok-2.0.2.dist-info/RECORD
clok-2.0.2.dist-info/WHEEL
clok-2.0.2.dist-info/entry_points.txt
clok-2.0.2.dist-info/metadata.json
clok-2.0.2.dist-info/top_level.txt
