Metadata-Version: 2.0
Name: clok
Version: 2.0.2
Summary: Listen to radio and set up alarms from your computer, control it from a web ui.
Home-page: http://github.com/fspot/clok
Author: fspot
Author-email: fred@fspot.org
License: BSD
Platform: UNKNOWN
Requires-Dist: bottle
Requires-Dist: docopt
Requires-Dist: pyradio
Requires-Dist: requests
Requires-Dist: tinydb
Requires-Dist: waitress
